{"$schema":"metaschema.yaml","name":"EBV Dataset Profile","abstract":"Identity of an EBV dataset: class, name, entities, metric, scope, DOI. Following GEO BON framework.","status":"under-development","dateTimeAddition":"2024-01-01T00:00:00Z","itemClass":"schema","register":"ogc-building-block-examples","version":"1.0","dateOfLastChange":"2024-01-01","sources":[{"title":"GEO BON EBV Framework","link":"https://geobon.org/ebvs/"}],"tags":["ebv","profile","geobon","identity"],"group":"EBV Specific","highlighted":true}
